optilogic/__init__.py
optilogic/pioneer/__init__.py
optilogic/pioneer/api/__init__.py
optilogic/pioneer/api/api.py
optilogic/pioneer/api/api_tests.py
optilogic/pioneer/api/api_utils.py
optilogic/pioneer/api/quick_tests/__init__.py
optilogic/pioneer/api/quick_tests/airline_hub_location_cbc.py
optilogic/pioneer/api/quick_tests/bash.py
optilogic/pioneer/api/quick_tests/job_key_self_aware.py
optilogic/pioneer/api/quick_tests/quick.py
optilogic/pioneer/api/quick_tests/sidecar.py
optilogic/pioneer/api/quick_tests/sleep.py
optilogic/pioneer/job_utils/__init__.py
optilogic/pioneer/job_utils/job_utils.py
optilogic-2.14.0.dist-info/LICENSE
optilogic-2.14.0.dist-info/METADATA
optilogic-2.14.0.dist-info/WHEEL
optilogic-2.14.0.dist-info/top_level.txt
optilogic-2.14.0.dist-info/RECORD
