Metadata-Version: 2.1
Name: optilogic
Version: 2.14.0
Summary: Tools for interfacing with Optilogic Jobs and APIs
Home-page: https://optilogic.com
Author: Optilogic
Author-email: support@optilogic.com
License: MIT
Project-URL: Documentation, https://api-docs.optilogic.app/documentation
Keywords: mip,mixed integer programming,network optimization,optimization,risk,simulation,supply chain design
Classifier: Programming Language :: Python
Classifier: Programming Language :: Python :: 3.8
Classifier: Programming Language :: Python :: 3.9
Classifier: Programming Language :: Python :: 3.10
Classifier: Programming Language :: Python :: 3.11
Requires-Python: >=3.8
License-File: LICENSE
Requires-Dist: cachetools
Requires-Dist: docopt
Requires-Dist: requests
